tct/__init__.py
tct/tct.py
pytct-0.0.1.dist-info/METADATA
pytct-0.0.1.dist-info/WHEEL
pytct-0.0.1.dist-info/top_level.txt
pytct-0.0.1.dist-info/RECORD
