Metadata-Version: 2.1
Name: pytct
Version: 0.0.1
Summary: Read, manipulate and visualize data taken by PSTCT by Particulars
Home-page: https://github.com/wiso/pytct
Author: Ruggero Turra
Author-email: ruggero.turra@cern.ch
License: UNKNOWN
Platform: UNKNOWN
Classifier: Programming Language :: Python :: 3
Classifier: Development Status :: 3 - Alpha
Classifier: Operating System :: OS Independent
Requires-Python: >=3.4
Requires-Dist: numpy
